odoo10_addon_hr_recruitment_candidate_multi_applicant-10.0.1.0.0.99.dev6-py2.7-nspkg.pth
odoo/addons/hr_recruitment_candidate_multi_applicant/README.rst
odoo/addons/hr_recruitment_candidate_multi_applicant/__init__.py
odoo/addons/hr_recruitment_candidate_multi_applicant/__manifest__.py
odoo/addons/hr_recruitment_candidate_multi_applicant/i18n/fr.po
odoo/addons/hr_recruitment_candidate_multi_applicant/i18n/hr_recruitment_candidate_multi_applicant.pot
odoo/addons/hr_recruitment_candidate_multi_applicant/models/__init__.py
odoo/addons/hr_recruitment_candidate_multi_applicant/models/hr_applicant.py
odoo/addons/hr_recruitment_candidate_multi_applicant/static/description/icon.png
odoo/addons/hr_recruitment_candidate_multi_applicant/tests/__init__.py
odoo/addons/hr_recruitment_candidate_multi_applicant/tests/test_multi_applicant.py
odoo/addons/hr_recruitment_candidate_multi_applicant/views/applicant.xml
odoo10_addon_hr_recruitment_candidate_multi_applicant-10.0.1.0.0.99.dev6.dist-info/METADATA
odoo10_addon_hr_recruitment_candidate_multi_applicant-10.0.1.0.0.99.dev6.dist-info/RECORD
odoo10_addon_hr_recruitment_candidate_multi_applicant-10.0.1.0.0.99.dev6.dist-info/WHEEL
odoo10_addon_hr_recruitment_candidate_multi_applicant-10.0.1.0.0.99.dev6.dist-info/namespace_packages.txt
odoo10_addon_hr_recruitment_candidate_multi_applicant-10.0.1.0.0.99.dev6.dist-info/top_level.txt
